greet/__init__.py
greet/location.py
greettest-0.1.0.dist-info/entry_points.txt
greettest-0.1.0.dist-info/WHEEL
greettest-0.1.0.dist-info/METADATA
greettest-0.1.0.dist-info/RECORD
